pretix_question_placeholders/__init__.py
pretix_question_placeholders/forms.py
pretix_question_placeholders/models.py
pretix_question_placeholders/placeholder.py
pretix_question_placeholders/signals.py
pretix_question_placeholders/urls.py
pretix_question_placeholders/views.py
pretix_question_placeholders/locale/de/LC_MESSAGES/django.mo
pretix_question_placeholders/locale/de/LC_MESSAGES/django.po
pretix_question_placeholders/locale/de_Informal/.gitkeep
pretix_question_placeholders/locale/de_Informal/LC_MESSAGES/django.mo
pretix_question_placeholders/locale/de_Informal/LC_MESSAGES/django.po
pretix_question_placeholders/migrations/0001_initial.py
pretix_question_placeholders/migrations/0002_auto_20210121_1406.py
pretix_question_placeholders/migrations/0003_condition_content_optional.py
pretix_question_placeholders/migrations/__init__.py
pretix_question_placeholders/static/pretix_question_placeholders/.gitkeep
pretix_question_placeholders/static/pretix_question_placeholders/placeholder.css
pretix_question_placeholders/static/pretix_question_placeholders/placeholder.js
pretix_question_placeholders/templates/pretix_question_placeholders/.gitkeep
pretix_question_placeholders/templates/pretix_question_placeholders/create.html
pretix_question_placeholders/templates/pretix_question_placeholders/delete.html
pretix_question_placeholders/templates/pretix_question_placeholders/edit.html
pretix_question_placeholders/templates/pretix_question_placeholders/list.html
pretix_question_placeholders-0.7.0.dist-info/licenses/LICENSE
pretix_question_placeholders-0.7.0.dist-info/METADATA
pretix_question_placeholders-0.7.0.dist-info/WHEEL
pretix_question_placeholders-0.7.0.dist-info/entry_points.txt
pretix_question_placeholders-0.7.0.dist-info/top_level.txt
pretix_question_placeholders-0.7.0.dist-info/RECORD
