Metadata-Version: 2.4
Name: pretix-question-placeholders
Version: 0.7.0
Summary: Add content to your emails based on the questions the customer answered, and the answer they gave.
Author-email: Tobias Kunze <r@rixx.de>
Maintainer-email: Tobias Kunze <r@rixx.de>
License: Apache
Project-URL: homepage, https://github.com/rixx/pretix-question-placeholders
Project-URL: repository, https://github.com/rixx/pretix-question-placeholders
Keywords: pretix
License-File: LICENSE
Dynamic: license-file
